{
  "content": [
    {
      "content": null,
      "created": "2023-08-25T00:47:04.945709Z",
      "format": null,
      "last_modified": "2023-08-25T00:46:40.293846Z",
      "mimetype": null,
      "name": "data-science-python-plotting.ipynb",
      "path": "data-science-python-plotting.ipynb",
      "size": 140859,
      "type": "notebook",
      "writable": true
    },
    {
      "content": null,
      "created": "2023-08-25T00:47:04.945709Z",
      "format": null,
      "last_modified": "2023-08-25T00:46:40.293846Z",
      "mimetype": null,
      "name": "data-science-python-multiprocessing.ipynb",
      "path": "data-science-python-multiprocessing.ipynb",
      "size": 43751,
      "type": "notebook",
      "writable": true
    },
    {
      "content": null,
      "created": "2023-08-25T00:47:04.941709Z",
      "format": null,
      "last_modified": "2023-08-25T00:46:40.277846Z",
      "mimetype": null,
      "name": "data-science-python-basics.ipynb",
      "path": "data-science-python-basics.ipynb",
      "size": 152633,
      "type": "notebook",
      "writable": true
    },
    {
      "content": null,
      "created": "2023-08-25T00:47:04.941709Z",
      "format": null,
      "last_modified": "2023-08-25T00:46:40.281846Z",
      "mimetype": null,
      "name": "data-science-python-exceptions.ipynb",
      "path": "data-science-python-exceptions.ipynb",
      "size": 11740,
      "type": "notebook",
      "writable": true
    },
    {
      "content": null,
      "created": "2023-08-25T00:47:04.945709Z",
      "format": null,
      "last_modified": "2023-08-25T00:46:40.297846Z",
      "mimetype": null,
      "name": "data-science-python-testing.ipynb",
      "path": "data-science-python-testing.ipynb",
      "size": 21940,
      "type": "notebook",
      "writable": true
    },
    {
      "content": null,
      "created": "2023-08-25T00:47:04.945709Z",
      "format": null,
      "last_modified": "2023-08-25T00:46:40.297846Z",
      "mimetype": null,
      "name": "data-science-python-subprocess.ipynb",
      "path": "data-science-python-subprocess.ipynb",
      "size": 22020,
      "type": "notebook",
      "writable": true
    },
    {
      "content": null,
      "created": "2023-08-25T00:47:04.941709Z",
      "format": null,
      "last_modified": "2023-08-25T00:46:40.281846Z",
      "mimetype": null,
      "name": "data-science-python-files.ipynb",
      "path": "data-science-python-files.ipynb",
      "size": 40902,
      "type": "notebook",
      "writable": true
    },
    {
      "content": null,
      "created": "2023-08-25T00:47:04.941709Z",
      "format": null,
      "last_modified": "2023-08-25T00:46:40.285846Z",
      "mimetype": null,
      "name": "data-science-python-functions.ipynb",
      "path": "data-science-python-functions.ipynb",
      "size": 35890,
      "type": "notebook",
      "writable": true
    },
    {
      "content": null,
      "created": "2023-08-25T00:47:04.941709Z",
      "format": null,
      "last_modified": "2023-08-25T00:46:40.277846Z",
      "mimetype": null,
      "name": "data-science-python-basics-recap.ipynb",
      "path": "data-science-python-basics-recap.ipynb",
      "size": 30144,
      "type": "notebook",
      "writable": true
    },
    {
      "content": null,
      "created": "2023-08-25T00:47:04.937709Z",
      "format": null,
      "last_modified": "2023-08-25T00:46:40.273846Z",
      "mimetype": null,
      "name": "data-science-python-advanced-np-pd.ipynb",
      "path": "data-science-python-advanced-np-pd.ipynb",
      "size": 111668,
      "type": "notebook",
      "writable": true
    },
    {
      "content": null,
      "created": "2023-08-25T00:47:04.941709Z",
      "format": null,
      "last_modified": "2023-08-25T00:46:40.289846Z",
      "mimetype": null,
      "name": "data-science-python-loops.ipynb",
      "path": "data-science-python-loops.ipynb",
      "size": 41317,
      "type": "notebook",
      "writable": true
    },
    {
      "content": null,
      "created": "2023-08-25T00:47:04.941709Z",
      "format": null,
      "last_modified": "2023-08-25T00:46:40.285846Z",
      "mimetype": null,
      "name": "data-science-python-glob.ipynb",
      "path": "data-science-python-glob.ipynb",
      "size": 9165,
      "type": "notebook",
      "writable": true
    },
    {
      "content": null,
      "created": "2023-08-25T00:47:04.945709Z",
      "format": null,
      "last_modified": "2023-08-25T00:46:40.301846Z",
      "mimetype": null,
      "name": "data-science-python-types.ipynb",
      "path": "data-science-python-types.ipynb",
      "size": 27481,
      "type": "notebook",
      "writable": true
    },
    {
      "content": null,
      "created": "2023-08-25T00:47:04.941709Z",
      "format": null,
      "last_modified": "2023-08-25T00:46:40.289846Z",
      "mimetype": null,
      "name": "data-science-python-iterables.ipynb",
      "path": "data-science-python-iterables.ipynb",
      "size": 64522,
      "type": "notebook",
      "writable": true
    },
    {
      "content": null,
      "created": "2023-08-25T00:47:04.941709Z",
      "format": null,
      "last_modified": "2023-08-25T00:46:40.281846Z",
      "mimetype": null,
      "name": "data-science-python-flow.ipynb",
      "path": "data-science-python-flow.ipynb",
      "size": 39880,
      "type": "notebook",
      "writable": true
    },
    {
      "content": null,
      "created": "2023-08-25T00:47:04.945709Z",
      "format": null,
      "last_modified": "2023-08-25T00:46:40.301846Z",
      "mimetype": null,
      "name": "data-science-python-typing.ipynb",
      "path": "data-science-python-typing.ipynb",
      "size": 130877,
      "type": "notebook",
      "writable": true
    },
    {
      "content": null,
      "created": "2023-08-25T00:47:04.945709Z",
      "format": null,
      "last_modified": "2023-08-25T00:46:40.289846Z",
      "mimetype": null,
      "name": "data-science-python-math.ipynb",
      "path": "data-science-python-math.ipynb",
      "size": 25731,
      "type": "notebook",
      "writable": true
    }
  ],
  "created": "2023-08-25T00:47:04.945709Z",
  "format": "json",
  "last_modified": "2023-08-25T00:47:04.945709Z",
  "mimetype": null,
  "name": "",
  "path": "",
  "size": null,
  "type": "directory",
  "writable": true
}